[{"model": "admin.logentry", "pk": 85, "fields": {"action_time": "2024-10-01T05:06:27.165Z", "user": 13, "content_type": 8, "object_id": "21", "object_repr": "test", "action_flag": 1, "change_message": "[{\"added\": {}}]"}}, {"model": "admin.logentry", "pk": 86, "fields": {"action_time": "2024-10-01T05:17:22.007Z", "user": 13, "content_type": 6, "object_id": "12", "object_repr": "test", "action_flag": 1, "change_message": "[{\"added\": {}}]"}}, {"model": "admin.logentry", "pk": 87, "fields": {"action_time": "2024-10-01T05:17:29.336Z", "user": 13, "content_type": 9, "object_id": "14", "object_repr": "test", "action_flag": 1, "change_message": "[{\"added\": {}}]"}}, {"model": "admin.logentry", "pk": 88, "fields": {"action_time": "2024-10-01T05:17:34.979Z", "user": 13, "content_type": 6, "object_id": "12", "object_repr": "test", "action_flag": 2, "change_message": "[{\"changed\": {\"fields\": [\"Subscriber count\"]}}]"}}, {"model": "admin.logentry", "pk": 89, "fields": {"action_time": "2024-10-01T05:18:47.368Z", "user": 13, "content_type": 5, "object_id": "1234", "object_repr": "1234", "action_flag": 2, "change_message": "[{\"changed\": {\"fields\": [\"Approved\"]}}]"}}, {"model": "admin.logentry", "pk": 90, "fields": {"action_time": "2024-10-01T05:50:25.548Z", "user": 13, "content_type": 5, "object_id": "mobile", "object_repr": "mobile", "action_flag": 2, "change_message": "[{\"changed\": {\"fields\": [\"Approved\"]}}]"}}, {"model": "admin.logentry", "pk": 91, "fields": {"action_time": "2024-10-01T07:09:17.861Z", "user": 13, "content_type": 8, "object_id": "23", "object_repr": "Ttdhd", "action_flag": 3, "change_message": ""}}, {"model": "admin.logentry", "pk": 92, "fields": {"action_time": "2024-10-01T07:09:17.878Z", "user": 13, "content_type": 8, "object_id": "22", "object_repr": "test", "action_flag": 3, "change_message": ""}}, {"model": "admin.logentry", "pk": 93, "fields": {"action_time": "2024-10-01T07:09:17.893Z", "user": 13, "content_type": 8, "object_id": "21", "object_repr": "test", "action_flag": 3, "change_message": ""}}, {"model": "admin.logentry", "pk": 94, "fields": {"action_time": "2024-10-01T07:09:23.762Z", "user": 13, "content_type": 6, "object_id": "14", "object_repr": "mobile", "action_flag": 3, "change_message": ""}}, {"model": "admin.logentry", "pk": 95, "fields": {"action_time": "2024-10-01T07:09:23.834Z", "user": 13, "content_type": 6, "object_id": "13", "object_repr": "1234", "action_flag": 3, "change_message": ""}}, {"model": "admin.logentry", "pk": 96, "fields": {"action_time": "2024-10-01T07:09:24.030Z", "user": 13, "content_type": 6, "object_id": "12", "object_repr": "test", "action_flag": 3, "change_message": ""}}, {"model": "admin.logentry", "pk": 97, "fields": {"action_time": "2024-10-01T07:09:32.086Z", "user": 13, "content_type": 9, "object_id": "15", "object_repr": "1234", "action_flag": 3, "change_message": ""}}, {"model": "admin.logentry", "pk": 98, "fields": {"action_time": "2024-10-01T07:09:32.235Z", "user": 13, "content_type": 9, "object_id": "16", "object_repr": "mobile", "action_flag": 3, "change_message": ""}}, {"model": "admin.logentry", "pk": 99, "fields": {"action_time": "2024-10-01T07:09:32.457Z", "user": 13, "content_type": 9, "object_id": "14", "object_repr": "test", "action_flag": 3, "change_message": ""}}, {"model": "admin.logentry", "pk": 100, "fields": {"action_time": "2024-10-03T00:33:22.552Z", "user": 13, "content_type": 5, "object_id": "test", "object_repr": "test", "action_flag": 2, "change_message": "[{\"changed\": {\"fields\": [\"Approved\"]}}]"}}, {"model": "auth.permission", "pk": 1, "fields": {"name": "Can add permission", "content_type": 1, "codename": "add_permission"}}, {"model": "auth.permission", "pk": 2, "fields": {"name": "Can change permission", "content_type": 1, "codename": "change_permission"}}, {"model": "auth.permission", "pk": 3, "fields": {"name": "Can delete permission", "content_type": 1, "codename": "delete_permission"}}, {"model": "auth.permission", "pk": 4, "fields": {"name": "Can view permission", "content_type": 1, "codename": "view_permission"}}, {"model": "auth.permission", "pk": 5, "fields": {"name": "Can add group", "content_type": 2, "codename": "add_group"}}, {"model": "auth.permission", "pk": 6, "fields": {"name": "Can change group", "content_type": 2, "codename": "change_group"}}, {"model": "auth.permission", "pk": 7, "fields": {"name": "Can delete group", "content_type": 2, "codename": "delete_group"}}, {"model": "auth.permission", "pk": 8, "fields": {"name": "Can view group", "content_type": 2, "codename": "view_group"}}, {"model": "auth.permission", "pk": 9, "fields": {"name": "Can add content type", "content_type": 3, "codename": "add_contenttype"}}, {"model": "auth.permission", "pk": 10, "fields": {"name": "Can change content type", "content_type": 3, "codename": "change_contenttype"}}, {"model": "auth.permission", "pk": 11, "fields": {"name": "Can delete content type", "content_type": 3, "codename": "delete_contenttype"}}, {"model": "auth.permission", "pk": 12, "fields": {"name": "Can view content type", "content_type": 3, "codename": "view_contenttype"}}, {"model": "auth.permission", "pk": 13, "fields": {"name": "Can add comment", "content_type": 4, "codename": "add_comment"}}, {"model": "auth.permission", "pk": 14, "fields": {"name": "Can change comment", "content_type": 4, "codename": "change_comment"}}, {"model": "auth.permission", "pk": 15, "fields": {"name": "Can delete comment", "content_type": 4, "codename": "delete_comment"}}, {"model": "auth.permission", "pk": 16, "fields": {"name": "Can view comment", "content_type": 4, "codename": "view_comment"}}, {"model": "auth.permission", "pk": 17, "fields": {"name": "Can add signup request", "content_type": 5, "codename": "add_signuprequest"}}, {"model": "auth.permission", "pk": 18, "fields": {"name": "Can change signup request", "content_type": 5, "codename": "change_signuprequest"}}, {"model": "auth.permission", "pk": 19, "fields": {"name": "Can delete signup request", "content_type": 5, "codename": "delete_signuprequest"}}, {"model": "auth.permission", "pk": 20, "fields": {"name": "Can view signup request", "content_type": 5, "codename": "view_signuprequest"}}, {"model": "auth.permission", "pk": 21, "fields": {"name": "Can add unit", "content_type": 6, "codename": "add_unit"}}, {"model": "auth.permission", "pk": 22, "fields": {"name": "Can change unit", "content_type": 6, "codename": "change_unit"}}, {"model": "auth.permission", "pk": 23, "fields": {"name": "Can delete unit", "content_type": 6, "codename": "delete_unit"}}, {"model": "auth.permission", "pk": 24, "fields": {"name": "Can view unit", "content_type": 6, "codename": "view_unit"}}, {"model": "auth.permission", "pk": 25, "fields": {"name": "Can add reply", "content_type": 7, "codename": "add_reply"}}, {"model": "auth.permission", "pk": 26, "fields": {"name": "Can change reply", "content_type": 7, "codename": "change_reply"}}, {"model": "auth.permission", "pk": 27, "fields": {"name": "Can delete reply", "content_type": 7, "codename": "delete_reply"}}, {"model": "auth.permission", "pk": 28, "fields": {"name": "Can view reply", "content_type": 7, "codename": "view_reply"}}, {"model": "auth.permission", "pk": 29, "fields": {"name": "Can add post", "content_type": 8, "codename": "add_post"}}, {"model": "auth.permission", "pk": 30, "fields": {"name": "Can change post", "content_type": 8, "codename": "change_post"}}, {"model": "auth.permission", "pk": 31, "fields": {"name": "Can delete post", "content_type": 8, "codename": "delete_post"}}, {"model": "auth.permission", "pk": 32, "fields": {"name": "Can view post", "content_type": 8, "codename": "view_post"}}, {"model": "auth.permission", "pk": 33, "fields": {"name": "Can add user", "content_type": 9, "codename": "add_customuser"}}, {"model": "auth.permission", "pk": 34, "fields": {"name": "Can change user", "content_type": 9, "codename": "change_customuser"}}, {"model": "auth.permission", "pk": 35, "fields": {"name": "Can delete user", "content_type": 9, "codename": "delete_customuser"}}, {"model": "auth.permission", "pk": 36, "fields": {"name": "Can view user", "content_type": 9, "codename": "view_customuser"}}, {"model": "auth.permission", "pk": 37, "fields": {"name": "Can add log entry", "content_type": 10, "codename": "add_logentry"}}, {"model": "auth.permission", "pk": 38, "fields": {"name": "Can change log entry", "content_type": 10, "codename": "change_logentry"}}, {"model": "auth.permission", "pk": 39, "fields": {"name": "Can delete log entry", "content_type": 10, "codename": "delete_logentry"}}, {"model": "auth.permission", "pk": 40, "fields": {"name": "Can view log entry", "content_type": 10, "codename": "view_logentry"}}, {"model": "auth.permission", "pk": 41, "fields": {"name": "Can add session", "content_type": 11, "codename": "add_session"}}, {"model": "auth.permission", "pk": 42, "fields": {"name": "Can change session", "content_type": 11, "codename": "change_session"}}, {"model": "auth.permission", "pk": 43, "fields": {"name": "Can delete session", "content_type": 11, "codename": "delete_session"}}, {"model": "auth.permission", "pk": 44, "fields": {"name": "Can view session", "content_type": 11, "codename": "view_session"}}, {"model": "auth.permission", "pk": 45, "fields": {"name": "Can add category", "content_type": 12, "codename": "add_category"}}, {"model": "auth.permission", "pk": 46, "fields": {"name": "Can change category", "content_type": 12, "codename": "change_category"}}, {"model": "auth.permission", "pk": 47, "fields": {"name": "Can delete category", "content_type": 12, "codename": "delete_category"}}, {"model": "auth.permission", "pk": 48, "fields": {"name": "Can view category", "content_type": 12, "codename": "view_category"}}, {"model": "contenttypes.contenttype", "pk": 1, "fields": {"app_label": "auth", "model": "permission"}}, {"model": "contenttypes.contenttype", "pk": 2, "fields": {"app_label": "auth", "model": "group"}}, {"model": "contenttypes.contenttype", "pk": 3, "fields": {"app_label": "contenttypes", "model": "contenttype"}}, {"model": "contenttypes.contenttype", "pk": 4, "fields": {"app_label": "milble_app", "model": "comment"}}, {"model": "contenttypes.contenttype", "pk": 5, "fields": {"app_label": "milble_app", "model": "signuprequest"}}, {"model": "contenttypes.contenttype", "pk": 6, "fields": {"app_label": "milble_app", "model": "unit"}}, {"model": "contenttypes.contenttype", "pk": 7, "fields": {"app_label": "milble_app", "model": "reply"}}, {"model": "contenttypes.contenttype", "pk": 8, "fields": {"app_label": "milble_app", "model": "post"}}, {"model": "contenttypes.contenttype", "pk": 9, "fields": {"app_label": "milble_app", "model": "customuser"}}, {"model": "contenttypes.contenttype", "pk": 10, "fields": {"app_label": "admin", "model": "logentry"}}, {"model": "contenttypes.contenttype", "pk": 11, "fields": {"app_label": "sessions", "model": "session"}}, {"model": "contenttypes.contenttype", "pk": 12, "fields": {"app_label": "milble_app", "model": "category"}}, {"model": "sessions.session", "pk": "081ruaz6v4aolk3sf2abzpt4pgdbhz0i", "fields": {"session_data": ".eJxVjDsOwjAQBe_iGll28JeSPmew1rtrHECOFCcV4u4QKQW0b2beSyTY1pq2zkuaSFyE9uL0O2bAB7ed0B3abZY4t3WZstwVedAux5n4eT3cv4MKvX5rVl57GlhT9KWADgOAZpsLk82gLFvlQqR4NoFyIYdgTHGMFkPG6EG8Py6OOWQ:1swahd:BClO7ZUcp9BoJwAJm1Rd6TNIZthhS02n8r731NRofXA", "expire_date": "2024-10-18T05:18:09.887Z"}}, {"model": "sessions.session", "pk": "09iot9mmk355igrshmcxd9eyk5launt3", "fields": {"session_data": ".eJxVjMEOwiAQRP-FsyFduxTq0bvfQNhdkKqhSWlPxn-XJj3ocea9mbfyYVuz32pc_CTqokCdfjsK_IxlB_II5T5rnsu6TKR3RR-06tss8XU93L-DHGpuawMUATtCICsGsKchOIc8tEChY4sRG8OEyY3ozmMvyCwW2LDBBOrzBdLdN5U:1su3Vf:ErExWZ7J5HTwfFBaQlVzGMlYAYbJke4f2DYN7WwughI", "expire_date": "2024-10-11T05:27:19.538Z"}}, {"model": "sessions.session", "pk": "0km8xt5xqthf7nlk908ecxwy6dio3avf", "fields": {"session_data": ".eJxVjDsOwjAQBe_iGll28JeSPmew1rtrHECOFCcV4u4QKQW0b2beSyTY1pq2zkuaSFyE9uL0O2bAB7ed0B3abZY4t3WZstwVedAux5n4eT3cv4MKvX5rVl57GlhT9KWADgOAZpsLk82gLFvlQqR4NoFyIYdgTHGMFkPG6EG8Py6OOWQ:1swahd:BClO7ZUcp9BoJwAJm1Rd6TNIZthhS02n8r731NRofXA", "expire_date": "2024-10-18T05:18:09.682Z"}}, {"model": "sessions.session", "pk": "0u6vvpnrvjrd870xmnrvv064n722e9xb", "fields": {"session_data": ".eJxVjDsOwjAQBe_iGll28JeSPmew1rtrHECOFCcV4u4QKQW0b2beSyTY1pq2zkuaSFyE9uL0O2bAB7ed0B3abZY4t3WZstwVedAux5n4eT3cv4MKvX5rVl57GlhT9KWADgOAZpsLk82gLFvlQqR4NoFyIYdgTHGMFkPG6EG8Py6OOWQ:1swaTE:sBN5s_6yR7lnhwJvZGQA8eseaPiXdml6Yw1pyVqI11I", "expire_date": "2024-10-18T05:03:16.435Z"}}, {"model": "sessions.session", "pk": "0wfae7ems19uzpzqahqw8i2tyyh3knqm", "fields": {"session_data": ".eJxVjDsOwjAQBe_iGll28JeSPmew1rtrHECOFCcV4u4QKQW0b2beSyTY1pq2zkuaSFyE9uL0O2bAB7ed0B3abZY4t3WZstwVedAux5n4eT3cv4MKvX5rVl57GlhT9KWADgOAZpsLk82gLFvlQqR4NoFyIYdgTHGMFkPG6EG8Py6OOWQ:1swaTA:mQBlH0ZLge4vjpfC5ihiUgk-hyNZq9uhpbNj-_f-lck", "expire_date": "2024-10-18T05:03:12.859Z"}}, {"model": "sessions.session", "pk": "0ysa9er8sdgej759uirg9r7ax3qxrzfj", "fields": {"session_data": ".eJxVjDsOwjAQBe_iGll28JeSPmew1rtrHECOFCcV4u4QKQW0b2beSyTY1pq2zkuaSFyE9uL0O2bAB7ed0B3abZY4t3WZstwVedAux5n4eT3cv4MKvX5rVl57GlhT9KWADgOAZpsLk82gLFvlQqR4NoFyIYdgTHGMFkPG6EG8Py6OOWQ:1swab7:b4Ejx6iJumW0XaueEE2Igpr1T__BsuuYwLyQ0upgfPM", "expire_date": "2024-10-18T05:11:25.440Z"}}, {"model": "sessions.session", "pk": "1cxdgkeiegkvk21xi364lv1roxmouiga", "fields": {"session_data": ".eJxVjDsOwjAQBe_iGll28JeSPmew1rtrHECOFCcV4u4QKQW0b2beSyTY1pq2zkuaSFyE9uL0O2bAB7ed0B3abZY4t3WZstwVedAux5n4eT3cv4MKvX5rVl57GlhT9KWADgOAZpsLk82gLFvlQqR4NoFyIYdgTHGMFkPG6EG8Py6OOWQ:1swaTE:sBN5s_6yR7lnhwJvZGQA8eseaPiXdml6Yw1pyVqI11I", "expire_date": "2024-10-18T05:03:16.162Z"}}, {"model": "sessions.session", "pk": "1yigc3a1lkv8wwucq3xlzwvvfk5ygwhl", "fields": {"session_data": ".eJxVjDsOwjAQBe_iGll28JeSPmew1rtrHECOFCcV4u4QKQW0b2beSyTY1pq2zkuaSFyE9uL0O2bAB7ed0B3abZY4t3WZstwVedAux5n4eT3cv4MKvX5rVl57GlhT9KWADgOAZpsLk82gLFvlQqR4NoFyIYdgTHGMFkPG6EG8Py6OOWQ:1swaXc:mzRynN5TJeqHhIYKCu7ogdYlb-IvuTkf9LloUCntTOU", "expire_date": "2024-10-18T05:07:48.036Z"}}, {"model": "sessions.session", "pk": "315mookfsjw8g1ypmdnz67xl09obzz3f", "fields": {"session_data": ".eJxVjDsOwjAQBe_iGll28JeSPmew1rtrHECOFCcV4u4QKQW0b2beSyTY1pq2zkuaSFyE9uL0O2bAB7ed0B3abZY4t3WZstwVedAux5n4eT3cv4MKvX5rVl57GlhT9KWADgOAZpsLk82gLFvlQqR4NoFyIYdgTHGMFkPG6EG8Py6OOWQ:1swadf:r-dz7wHAAEeu4YtbEA89cdlM9EnrDioFP5SRR2AC9BI", "expire_date": "2024-10-18T05:14:03.236Z"}}, {"model": "sessions.session", "pk": "3sycpjc9mnlwi1h7xdltal0x9josmqca", "fields": {"session_data": ".eJxVjDsOwjAQBe_iGll28JeSPmew1rtrHECOFCcV4u4QKQW0b2beSyTY1pq2zkuaSFyE9uL0O2bAB7ed0B3abZY4t3WZstwVedAux5n4eT3cv4MKvX5rVl57GlhT9KWADgOAZpsLk82gLFvlQqR4NoFyIYdgTHGMFkPG6EG8Py6OOWQ:1swahF:M0JkNPtllfT1VgfXltaqhV_0bg1mLtF2aXeXb31vPGk", "expire_date": "2024-10-18T05:17:45.621Z"}}, {"model": "sessions.session", "pk": "3wwlsnhmevgl5t17uagzgbk0ou0lg3dh", "fields": {"session_data": ".eJxVjDsOwjAQBe_iGll28JeSPmew1rtrHECOFCcV4u4QKQW0b2beSyTY1pq2zkuaSFyE9uL0O2bAB7ed0B3abZY4t3WZstwVedAux5n4eT3cv4MKvX5rVl57GlhT9KWADgOAZpsLk82gLFvlQqR4NoFyIYdgTHGMFkPG6EG8Py6OOWQ:1swab7:b4Ejx6iJumW0XaueEE2Igpr1T__BsuuYwLyQ0upgfPM", "expire_date": "2024-10-18T05:11:25.512Z"}}, {"model": "sessions.session", "pk": "45qld4rtmpz0gyhmqk0xwjlembokvnvl", "fields": {"session_data": ".eJxVjDsOwjAQBe_iGll28JeSPmew1rtrHECOFCcV4u4QKQW0b2beSyTY1pq2zkuaSFyE9uL0O2bAB7ed0B3abZY4t3WZstwVedAux5n4eT3cv4MKvX5rVl57GlhT9KWADgOAZpsLk82gLFvlQqR4NoFyIYdgTHGMFkPG6EG8Py6OOWQ:1swahF:M0JkNPtllfT1VgfXltaqhV_0bg1mLtF2aXeXb31vPGk", "expire_date": "2024-10-18T05:17:45.784Z"}}, {"model": "sessions.session", "pk": "4z6lla2ggmhj3cfr4onqb067v3nb2x01", "fields": {"session_data": ".eJxVjDsOwjAQBe_iGll28JeSPmew1rtrHECOFCcV4u4QKQW0b2beSyTY1pq2zkuaSFyE9uL0O2bAB7ed0B3abZY4t3WZstwVedAux5n4eT3cv4MKvX5rVl57GlhT9KWADgOAZpsLk82gLFvlQqR4NoFyIYdgTHGMFkPG6EG8Py6OOWQ:1swaTB:8gPd4SEoMZQk9toU_urJwgHbXn6Nyd9gkwWORzKSZzI", "expire_date": "2024-10-18T05:03:13.034Z"}}, {"model": "sessions.session", "pk": "5gtcud1fzrzfskngb3kcl7k9myxsqivx", "fields": {"session_data": "e30:1swaT5:NYk226olOIXdi3AULfctRtl-vWwP3Hwsdt8XiKBVNSM", "expire_date": "2024-10-18T05:03:07.467Z"}}, {"model": "sessions.session", "pk": "76m7uxkpvoile22su5hl85miceamhz2a", "fields": {"session_data": "e30:1swaT6:q4RuSe8eAfFBQRvUHtXjaGD_PeI4-63qkx8wkPylPH0", "expire_date": "2024-10-18T05:03:08.166Z"}}, {"model": "sessions.session", "pk": "7agus6glzocz6bd6igidm1364wo8ss6t", "fields": {"session_data": ".eJxVjDsOwjAQBe_iGll28JeSPmew1rtrHECOFCcV4u4QKQW0b2beSyTY1pq2zkuaSFyE9uL0O2bAB7ed0B3abZY4t3WZstwVedAux5n4eT3cv4MKvX5rVl57GlhT9KWADgOAZpsLk82gLFvlQqR4NoFyIYdgTHGMFkPG6EG8Py6OOWQ:1swaTB:8gPd4SEoMZQk9toU_urJwgHbXn6Nyd9gkwWORzKSZzI", "expire_date": "2024-10-18T05:03:13.080Z"}}, {"model": "sessions.session", "pk": "7ifiuaekqiagxs4j7w0rwz6tnv23q0x1", "fields": {"session_data": ".eJxVjDsOwjAQBe_iGll28JeSPmew1rtrHECOFCcV4u4QKQW0b2beSyTY1pq2zkuaSFyE9uL0O2bAB7ed0B3abZY4t3WZstwVedAux5n4eT3cv4MKvX5rVl57GlhT9KWADgOAZpsLk82gLFvlQqR4NoFyIYdgTHGMFkPG6EG8Py6OOWQ:1swaTB:8gPd4SEoMZQk9toU_urJwgHbXn6Nyd9gkwWORzKSZzI", "expire_date": "2024-10-18T05:03:13.245Z"}}, {"model": "sessions.session", "pk": "7opfa8ddlf7j0dkcajhzhbwwbez9ewcj", "fields": {"session_data": ".eJxVjDsOwjAQBe_iGll28JeSPmew1rtrHECOFCcV4u4QKQW0b2beSyTY1pq2zkuaSFyE9uL0O2bAB7ed0B3abZY4t3WZstwVedAux5n4eT3cv4MKvX5rVl57GlhT9KWADgOAZpsLk82gLFvlQqR4NoFyIYdgTHGMFkPG6EG8Py6OOWQ:1swaTD:DqLTIHEFf7oe3jInkV5dX4BeAeCxxmm8654CQYbtIlU", "expire_date": "2024-10-18T05:03:15.147Z"}}, {"model": "sessions.session", "pk": "8kghjvno6b73bnp5nskzbddtylfr24f1", "fields": {"session_data": ".eJxVjDsOwjAQBe_iGll28JeSPmew1rtrHECOFCcV4u4QKQW0b2beSyTY1pq2zkuaSFyE9uL0O2bAB7ed0B3abZY4t3WZstwVedAux5n4eT3cv4MKvX5rVl57GlhT9KWADgOAZpsLk82gLFvlQqR4NoFyIYdgTHGMFkPG6EG8Py6OOWQ:1swahe:dyYp9q6THa2seQQEvJn7M6DU9rcZVFIjyrkSfM2_HaY", "expire_date": "2024-10-18T05:18:10.253Z"}}, {"model": "sessions.session", "pk": "8ml6u2fevxn14ajbf9ni8txqns422ld4", "fields": {"session_data": ".eJxVjEEOwiAQRe_C2hDoUOi4dO8ZyAyMUjU0Ke3KeHfbpAvd_vfef6tI61Li2mSOY1Zn5dTpd2NKT6k7yA-q90mnqS7zyHpX9EGbvk5ZXpfD_Tso1MpWd_ZmwEnvyXEAmwYh74XRoqNucEEEQ_KMCMZmwwZhE41FAQspcK8-X9AjNz4:1su3W6:OpU0ixJog-NQEGFeh25IJv8YcTQ67JZGIgj67tavCy0", "expire_date": "2024-10-11T05:27:46.916Z"}}, {"model": "sessions.session", "pk": "8pg4k6kx7n9ynlzjankbt0oup4yr6c7a", "fields": {"session_data": ".eJxVjDsOwjAQBe_iGll28JeSPmew1rtrHECOFCcV4u4QKQW0b2beSyTY1pq2zkuaSFyE9uL0O2bAB7ed0B3abZY4t3WZstwVedAux5n4eT3cv4MKvX5rVl57GlhT9KWADgOAZpsLk82gLFvlQqR4NoFyIYdgTHGMFkPG6EG8Py6OOWQ:1swaTr:X7rY0hOFl7_gTZm3ozyvgNk0Xs7bNZyRVJgfKHmA7gI", "expire_date": "2024-10-18T05:03:55.989Z"}}, {"model": "sessions.session", "pk": "8v045xm4erolkfu6n68ys1a6gnpt2zc0", "fields": {"session_data": ".eJxVjDsOwjAQBe_iGll28JeSPmew1rtrHECOFCcV4u4QKQW0b2beSyTY1pq2zkuaSFyE9uL0O2bAB7ed0B3abZY4t3WZstwVedAux5n4eT3cv4MKvX5rVl57GlhT9KWADgOAZpsLk82gLFvlQqR4NoFyIYdgTHGMFkPG6EG8Py6OOWQ:1swahe:dyYp9q6THa2seQQEvJn7M6DU9rcZVFIjyrkSfM2_HaY", "expire_date": "2024-10-18T05:18:10.088Z"}}, {"model": "sessions.session", "pk": "9s8i9jdntso1dztn45yk8p2tplw30r1l", "fields": {"session_data": ".eJxVjDsOwjAQBe_iGll28JeSPmew1rtrHECOFCcV4u4QKQW0b2beSyTY1pq2zkuaSFyE9uL0O2bAB7ed0B3abZY4t3WZstwVedAux5n4eT3cv4MKvX5rVl57GlhT9KWADgOAZpsLk82gLFvlQqR4NoFyIYdgTHGMFkPG6EG8Py6OOWQ:1swahF:M0JkNPtllfT1VgfXltaqhV_0bg1mLtF2aXeXb31vPGk", "expire_date": "2024-10-18T05:17:45.476Z"}}, {"model": "sessions.session", "pk": "9y9e4d9xho6uet0vmfykphomr2c2ku08", "fields": {"session_data": ".eJxVjDsOwjAQBe_iGll28JeSPmew1rtrHECOFCcV4u4QKQW0b2beSyTY1pq2zkuaSFyE9uL0O2bAB7ed0B3abZY4t3WZstwVedAux5n4eT3cv4MKvX5rVl57GlhT9KWADgOAZpsLk82gLFvlQqR4NoFyIYdgTHGMFkPG6EG8Py6OOWQ:1swaTC:LZVudj7tKuHA6sPgvO_OGO9iP60RlvpReRvYcZWj3jE", "expire_date": "2024-10-18T05:03:14.539Z"}}, {"model": "sessions.session", "pk": "a5bzd9d7l3cdvk2veqb6td1pdqa4mz4s", "fields": {"session_data": ".eJxVjDsOwjAQBe_iGll28JeSPmew1rtrHECOFCcV4u4QKQW0b2beSyTY1pq2zkuaSFyE9uL0O2bAB7ed0B3abZY4t3WZstwVedAux5n4eT3cv4MKvX5rVl57GlhT9KWADgOAZpsLk82gLFvlQqR4NoFyIYdgTHGMFkPG6EG8Py6OOWQ:1swafI:tvdUZozoAG9IYeUxSl8O1Gn-bVSvUri5FPpzj63RWt4", "expire_date": "2024-10-18T05:15:44.893Z"}}, {"model": "sessions.session", "pk": "ao2qqs1un14ixa9tphlwaxx3tv46fcue", "fields": {"session_data": ".eJxVjDsOwjAQBe_iGll28JeSPmew1rtrHECOFCcV4u4QKQW0b2beSyTY1pq2zkuaSFyE9uL0O2bAB7ed0B3abZY4t3WZstwVedAux5n4eT3cv4MKvX5rVl57GlhT9KWADgOAZpsLk82gLFvlQqR4NoFyIYdgTHGMFkPG6EG8Py6OOWQ:1swacl:K3a54OiGgIO2easIqaR3QLD5RUv8ly9McT_CJFkLG6E", "expire_date": "2024-10-18T05:13:07.087Z"}}, {"model": "sessions.session", "pk": "bjmrxl9rnlmt4x0u1kz80lfx7jpdsmy6", "fields": {"session_data": ".eJxVjMEOwiAQRP-FsyFduxTq0bvfQNhdkKqhSWlPxn-XJj3ocea9mbfyYVuz32pc_CTqokCdfjsK_IxlB_II5T5rnsu6TKR3RR-06tss8XU93L-DHGpuawMUATtCICsGsKchOIc8tEChY4sRG8OEyY3ozmMvyCwW2LDBBOrzBdLdN5U:1suhJg:o1ZpxlAlLZWunbKoFHCigBMzUCx3gBr7DpztxI3fSCo", "expire_date": "2024-10-12T23:57:36.267Z"}}, {"model": "sessions.session", "pk": "btuj2p6e22sd325hmkb36sd2a7xws427", "fields": {"session_data": ".eJxVjEEOwiAQRe_C2pDCIAWX7j0DGYZBqgaS0q6Md7dNutDtf--_twi4LiWsnecwJXERCsTpd4xIT647SQ-s9yap1WWeotwVedAuby3x63q4f4GCvWzvPFIGF9GP7I13bNOZGZi2ApHS0SKa5CyYGJ1R2QBbO4A2A1ivMYP4fAE4Uzic:1svRs7:-Z8EWyrMnHF98h0VPWlfZi8xZsI5Nw8xBr0GdkeMRok", "expire_date": "2024-10-15T01:40:15.546Z"}}, {"model": "sessions.session", "pk": "cabggplu68alq677ds8zoxiwo3dlnwzc", "fields": {"session_data": ".eJxVjDsOwjAQBe_iGll28JeSPmew1rtrHECOFCcV4u4QKQW0b2beSyTY1pq2zkuaSFyE9uL0O2bAB7ed0B3abZY4t3WZstwVedAux5n4eT3cv4MKvX5rVl57GlhT9KWADgOAZpsLk82gLFvlQqR4NoFyIYdgTHGMFkPG6EG8Py6OOWQ:1swaWk:uFhaedU0uAXiFbcQlRKHDc4KvNnmNgEzwfNryVR2CZY", "expire_date": "2024-10-18T05:06:54.580Z"}}, {"model": "sessions.session", "pk": "cg4bofj5ke6bk087i9cq4cxc1cay17y4", "fields": {"session_data": ".eJxVjDsOwjAQBe_iGll28JeSPmew1rtrHECOFCcV4u4QKQW0b2beSyTY1pq2zkuaSFyE9uL0O2bAB7ed0B3abZY4t3WZstwVedAux5n4eT3cv4MKvX5rVl57GlhT9KWADgOAZpsLk82gLFvlQqR4NoFyIYdgTHGMFkPG6EG8Py6OOWQ:1swaTr:X7rY0hOFl7_gTZm3ozyvgNk0Xs7bNZyRVJgfKHmA7gI", "expire_date": "2024-10-18T05:03:55.879Z"}}, {"model": "sessions.session", "pk": "d2x0ifxtvveoi0puq6m0j8z7nt0pf34t", "fields": {"session_data": ".eJxVjDsOwjAQBe_iGll28JeSPmew1rtrHECOFCcV4u4QKQW0b2beSyTY1pq2zkuaSFyE9uL0O2bAB7ed0B3abZY4t3WZstwVedAux5n4eT3cv4MKvX5rVl57GlhT9KWADgOAZpsLk82gLFvlQqR4NoFyIYdgTHGMFkPG6EG8Py6OOWQ:1swaTB:8gPd4SEoMZQk9toU_urJwgHbXn6Nyd9gkwWORzKSZzI", "expire_date": "2024-10-18T05:03:13.901Z"}}, {"model": "sessions.session", "pk": "d9oeagbl2js1mjbahopxpz12gl1fn6uh", "fields": {"session_data": ".eJxVjDsOwjAQBe_iGll28JeSPmew1rtrHECOFCcV4u4QKQW0b2beSyTY1pq2zkuaSFyE9uL0O2bAB7ed0B3abZY4t3WZstwVedAux5n4eT3cv4MKvX5rVl57GlhT9KWADgOAZpsLk82gLFvlQqR4NoFyIYdgTHGMFkPG6EG8Py6OOWQ:1swaXb:MwztaNWjAZiaru1YbiFyFSpVUruQ8d_py83N-OHNYzQ", "expire_date": "2024-10-18T05:07:47.824Z"}}, {"model": "sessions.session", "pk": "dmofn1c522q9pbpux3mrgrjgvl4w7bev", "fields": {"session_data": ".eJxVjDsOwjAQBe_iGll28JeSPmew1rtrHECOFCcV4u4QKQW0b2beSyTY1pq2zkuaSFyE9uL0O2bAB7ed0B3abZY4t3WZstwVedAux5n4eT3cv4MKvX5rVl57GlhT9KWADgOAZpsLk82gLFvlQqR4NoFyIYdgTHGMFkPG6EG8Py6OOWQ:1swaTB:8gPd4SEoMZQk9toU_urJwgHbXn6Nyd9gkwWORzKSZzI", "expire_date": "2024-10-18T05:03:13.326Z"}}, {"model": "sessions.session", "pk": "e8lks29znruj3oix6hyslsj9su36obxo", "fields": {"session_data": ".eJxVjDsOwjAQBe_iGll28JeSPmew1rtrHECOFCcV4u4QKQW0b2beSyTY1pq2zkuaSFyE9uL0O2bAB7ed0B3abZY4t3WZstwVedAux5n4eT3cv4MKvX5rVl57GlhT9KWADgOAZpsLk82gLFvlQqR4NoFyIYdgTHGMFkPG6EG8Py6OOWQ:1swaWk:uFhaedU0uAXiFbcQlRKHDc4KvNnmNgEzwfNryVR2CZY", "expire_date": "2024-10-18T05:06:54.934Z"}}, {"model": "sessions.session", "pk": "eaoszloya1ltbnx8ghcckj9r6jbugi5q", "fields": {"session_data": ".eJxVjDsOwjAQBe_iGll28JeSPmew1rtrHECOFCcV4u4QKQW0b2beSyTY1pq2zkuaSFyE9uL0O2bAB7ed0B3abZY4t3WZstwVedAux5n4eT3cv4MKvX5rVl57GlhT9KWADgOAZpsLk82gLFvlQqR4NoFyIYdgTHGMFkPG6EG8Py6OOWQ:1swaVN:Suzb0zksi4J4otTjTebDqKvxVMr1jrZjOf_7kVgMeGw", "expire_date": "2024-10-18T05:05:29.671Z"}}, {"model": "sessions.session", "pk": "fo8uvbmaiog1ns1tv4qffx6zk44k7vgs", "fields": {"session_data": ".eJxVjDsOwjAQBe_iGll28JeSPmew1rtrHECOFCcV4u4QKQW0b2beSyTY1pq2zkuaSFyE9uL0O2bAB7ed0B3abZY4t3WZstwVedAux5n4eT3cv4MKvX5rVl57GlhT9KWADgOAZpsLk82gLFvlQqR4NoFyIYdgTHGMFkPG6EG8Py6OOWQ:1swaVN:Suzb0zksi4J4otTjTebDqKvxVMr1jrZjOf_7kVgMeGw", "expire_date": "2024-10-18T05:05:29.828Z"}}, {"model": "sessions.session", "pk": "g5dy68nqx8cmu388ebm4s9ytxio7cgbk", "fields": {"session_data": ".eJxVjDsOwjAQBe_iGll28JeSPmew1rtrHECOFCcV4u4QKQW0b2beSyTY1pq2zkuaSFyE9uL0O2bAB7ed0B3abZY4t3WZstwVedAux5n4eT3cv4MKvX5rVl57GlhT9KWADgOAZpsLk82gLFvlQqR4NoFyIYdgTHGMFkPG6EG8Py6OOWQ:1swacl:K3a54OiGgIO2easIqaR3QLD5RUv8ly9McT_CJFkLG6E", "expire_date": "2024-10-18T05:13:07.227Z"}}, {"model": "sessions.session", "pk": "g6091cftartlskdlneskol42frui8iol", "fields": {"session_data": ".eJxVjEEOwiAQRe_C2pDCIAWX7j0DGYZBqgaS0q6Md7dNutDtf--_twi4LiWsnecwJXERCsTpd4xIT647SQ-s9yap1WWeotwVedAuby3x63q4f4GCvWzvPFIGF9GP7I13bNOZGZi2ApHS0SKa5CyYGJ1R2QBbO4A2A1ivMYP4fAE4Uzic:1svV5K:y6gRsdnqKkwPlsOvOAn5Iu623Lbqwx3DU7eQ_eiXdzU", "expire_date": "2024-10-15T05:06:06.827Z"}}, {"model": "sessions.session", "pk": "gbkx1muryufq5xhfrkvj3520eu1ut66y", "fields": {"session_data": ".eJxVjDsOwjAQBe_iGll28JeSPmew1rtrHECOFCcV4u4QKQW0b2beSyTY1pq2zkuaSFyE9uL0O2bAB7ed0B3abZY4t3WZstwVedAux5n4eT3cv4MKvX5rVl57GlhT9KWADgOAZpsLk82gLFvlQqR4NoFyIYdgTHGMFkPG6EG8Py6OOWQ:1swafI:tvdUZozoAG9IYeUxSl8O1Gn-bVSvUri5FPpzj63RWt4", "expire_date": "2024-10-18T05:15:44.479Z"}}, {"model": "sessions.session", "pk": "gj40zyocblzotigm72as179ctmmpedil", "fields": {"session_data": ".eJxVjDsOwjAQBe_iGll28JeSPmew1rtrHECOFCcV4u4QKQW0b2beSyTY1pq2zkuaSFyE9uL0O2bAB7ed0B3abZY4t3WZstwVedAux5n4eT3cv4MKvX5rVl57GlhT9KWADgOAZpsLk82gLFvlQqR4NoFyIYdgTHGMFkPG6EG8Py6OOWQ:1swaWk:uFhaedU0uAXiFbcQlRKHDc4KvNnmNgEzwfNryVR2CZY", "expire_date": "2024-10-18T05:06:54.763Z"}}, {"model": "sessions.session", "pk": "gryzg0cr9h7c4p018odr6wrkyaup81gu", "fields": {"session_data": ".eJxVjDsOwjAQBe_iGll28JeSPmew1rtrHECOFCcV4u4QKQW0b2beSyTY1pq2zkuaSFyE9uL0O2bAB7ed0B3abZY4t3WZstwVedAux5n4eT3cv4MKvX5rVl57GlhT9KWADgOAZpsLk82gLFvlQqR4NoFyIYdgTHGMFkPG6EG8Py6OOWQ:1swaTD:DqLTIHEFf7oe3jInkV5dX4BeAeCxxmm8654CQYbtIlU", "expire_date": "2024-10-18T05:03:15.517Z"}}, {"model": "sessions.session", "pk": "h0ep60xqyhkse3r1d5zntxj7g21twn80", "fields": {"session_data": ".eJxVjDsOwjAQBe_iGll28JeSPmew1rtrHECOFCcV4u4QKQW0b2beSyTY1pq2zkuaSFyE9uL0O2bAB7ed0B3abZY4t3WZstwVedAux5n4eT3cv4MKvX5rVl57GlhT9KWADgOAZpsLk82gLFvlQqR4NoFyIYdgTHGMFkPG6EG8Py6OOWQ:1swaTA:mQBlH0ZLge4vjpfC5ihiUgk-hyNZq9uhpbNj-_f-lck", "expire_date": "2024-10-18T05:03:12.746Z"}}, {"model": "sessions.session", "pk": "h8ial1liqq1how143lqixgxhxib5ffnf", "fields": {"session_data": ".eJxVjDsOwjAQBe_iGll28JeSPmew1rtrHECOFCcV4u4QKQW0b2beSyTY1pq2zkuaSFyE9uL0O2bAB7ed0B3abZY4t3WZstwVedAux5n4eT3cv4MKvX5rVl57GlhT9KWADgOAZpsLk82gLFvlQqR4NoFyIYdgTHGMFkPG6EG8Py6OOWQ:1swab7:b4Ejx6iJumW0XaueEE2Igpr1T__BsuuYwLyQ0upgfPM", "expire_date": "2024-10-18T05:11:25.379Z"}}, {"model": "sessions.session", "pk": "hkr7cgahxsb1cr1p7tcllwupdnqmx9zp", "fields": {"session_data": ".eJxVjDsOwjAQBe_iGll28JeSPmew1rtrHECOFCcV4u4QKQW0b2beSyTY1pq2zkuaSFyE9uL0O2bAB7ed0B3abZY4t3WZstwVedAux5n4eT3cv4MKvX5rVl57GlhT9KWADgOAZpsLk82gLFvlQqR4NoFyIYdgTHGMFkPG6EG8Py6OOWQ:1swaTA:mQBlH0ZLge4vjpfC5ihiUgk-hyNZq9uhpbNj-_f-lck", "expire_date": "2024-10-18T05:03:12.911Z"}}, {"model": "sessions.session", "pk": "hzz6g3lewejw4btxkop0l0q6ry4t8y1c", "fields": {"session_data": ".eJxVjEEOwiAQRe_C2pAWKFNcuvcMZGYYpGpoUtqV8e7apAvd_vfef6mI21ri1mSJU1JnZdXpdyPkh9QdpDvW26x5rusykd4VfdCmr3OS5-Vw_w4KtvKtvfVEPYwdEvlgcRAUwBScdWkUEQrIgwHbU-AAnc85OMNsDAGLhazeH_rUOKA:1stjN6:qofeT8VRlZEiH4rTOBMX4rpoO9Vrhr6uEHVMSQllaOM", "expire_date": "2024-10-10T07:57:08.625Z"}}, {"model": "sessions.session", "pk": "i0rxf8zi11knnudx74e3kvvokb2vcd3i", "fields": {"session_data": ".eJxVjEEOwiAQRe_C2pDCIAWX7j0DGYZBqgaS0q6Md7dNutDtf--_twi4LiWsnecwJXERCsTpd4xIT647SQ-s9yap1WWeotwVedAuby3x63q4f4GCvWzvPFIGF9GP7I13bNOZGZi2ApHS0SKa5CyYGJ1R2QBbO4A2A1ivMYP4fAE4Uzic:1swZln:enpjElo8GcirB3g9lCeNTjdqa9mFqxGygJHBzVZetrM", "expire_date": "2024-10-18T04:18:23.342Z"}}, {"model": "sessions.session", "pk": "icd54nwjd8a6r6ugksh7x469vowusbil", "fields": {"session_data": ".eJxVjDsOwjAQBe_iGll28JeSPmew1rtrHECOFCcV4u4QKQW0b2beSyTY1pq2zkuaSFyE9uL0O2bAB7ed0B3abZY4t3WZstwVedAux5n4eT3cv4MKvX5rVl57GlhT9KWADgOAZpsLk82gLFvlQqR4NoFyIYdgTHGMFkPG6EG8Py6OOWQ:1swaTr:X7rY0hOFl7_gTZm3ozyvgNk0Xs7bNZyRVJgfKHmA7gI", "expire_date": "2024-10-18T05:03:55.778Z"}}, {"model": "sessions.session", "pk": "ise2hx6i2595bx18j39khzg57zrhgt4y", "fields": {"session_data": ".eJxVjEEOwiAQRe_C2pDCIAWX7j0DGYZBqgaS0q6Md7dNutDtf--_twi4LiWsnecwJXERCsTpd4xIT647SQ-s9yap1WWeotwVedAuby3x63q4f4GCvWzvPFIGF9GP7I13bNOZGZi2ApHS0SKa5CyYGJ1R2QBbO4A2A1ivMYP4fAE4Uzic:1sw9mO:UZUVcL2g_GR7ugH1Dvjvd4oLYve2meF7FBThP8jWlYI", "expire_date": "2024-10-17T00:33:16.444Z"}}, {"model": "sessions.session", "pk": "ivni211d4dsj0cecyuxwkz2dypnk7am7", "fields": {"session_data": ".eJxVjDsOwjAQBe_iGll28JeSPmew1rtrHECOFCcV4u4QKQW0b2beSyTY1pq2zkuaSFyE9uL0O2bAB7ed0B3abZY4t3WZstwVedAux5n4eT3cv4MKvX5rVl57GlhT9KWADgOAZpsLk82gLFvlQqR4NoFyIYdgTHGMFkPG6EG8Py6OOWQ:1swaTs:ccbwn83OoBcWUSypbssv-ez9uB9SsrMeqrxc38ZTNrs", "expire_date": "2024-10-18T05:03:56.143Z"}}, {"model": "sessions.session", "pk": "j2flpjl6w9ypt2dwt55ouazgi0c48ttu", "fields": {"session_data": ".eJxVjMsOwiAQRf-FtSEgb5fu_QYywIxUDSSlXRn_3TbpQrf3nHPfLMK61LgOnONU2IUFdvrdEuQnth2UB7R757m3ZZ4S3xV-0MFvveDrerh_BxVG3WqhVKIsg3fCGBO09tkjFQzgAmrhggAiBUJbS1bCZsoirEU6q5QJCvt8AdgPOBY:1svAYl:NgOWgzLYcknNqxqLjlRBipNA_TwXOMPzXOWMale0-x0", "expire_date": "2024-10-14T07:11:07.666Z"}}, {"model": "sessions.session", "pk": "j402rfs3jwcwfws6prmv96dp8piywvpw", "fields": {"session_data": ".eJxVjDsOwjAQBe_iGll28JeSPmew1rtrHECOFCcV4u4QKQW0b2beSyTY1pq2zkuaSFyE9uL0O2bAB7ed0B3abZY4t3WZstwVedAux5n4eT3cv4MKvX5rVl57GlhT9KWADgOAZpsLk82gLFvlQqR4NoFyIYdgTHGMFkPG6EG8Py6OOWQ:1swaTA:mQBlH0ZLge4vjpfC5ihiUgk-hyNZq9uhpbNj-_f-lck", "expire_date": "2024-10-18T05:03:12.082Z"}}, {"model": "sessions.session", "pk": "j70l8btn3wvqeg3q44d1nrj9cz1bs5ul", "fields": {"session_data": ".eJxVjMsOwiAQRf-FtSEUyqMu3fsNZIYZpGogKe3K-O_apAvd3nPOfYkI21ri1nmJM4mz0OL0uyGkB9cd0B3qrcnU6rrMKHdFHrTLayN-Xg7376BAL986Bz2oZDmgY8bRkGMLMAIxu-yNGjKhV8p7jToBBWemCU3w1oTgEJx4fwACozg8:1su03z:tP9Tuot0JBQOmEWyJe21p8g4dFrUFCIxsLqTSrbcdRw", "expire_date": "2024-10-11T01:46:31.376Z"}}, {"model": "sessions.session", "pk": "ja3q8rrj4jma137qaxolxxkj9g4m3cq3", "fields": {"session_data": "e30:1swaT4:Onw-aRYE3YNsm_D9pZJtGVDO0xO2non-kJD95HCd7n4", "expire_date": "2024-10-18T05:03:06.264Z"}}, {"model": "sessions.session", "pk": "jgm39rzox866l48x1qpw849isokuuld1", "fields": {"session_data": ".eJxVjDsOwjAQBe_iGll28JeSPmew1rtrHECOFCcV4u4QKQW0b2beSyTY1pq2zkuaSFyE9uL0O2bAB7ed0B3abZY4t3WZstwVedAux5n4eT3cv4MKvX5rVl57GlhT9KWADgOAZpsLk82gLFvlQqR4NoFyIYdgTHGMFkPG6EG8Py6OOWQ:1swahF:M0JkNPtllfT1VgfXltaqhV_0bg1mLtF2aXeXb31vPGk", "expire_date": "2024-10-18T05:17:45.933Z"}}, {"model": "sessions.session", "pk": "kbdx0c8hctfqvl90fg9racb4tsqmqq50", "fields": {"session_data": ".eJxVjDsOwjAQBe_iGll28JeSPmew1rtrHECOFCcV4u4QKQW0b2beSyTY1pq2zkuaSFyE9uL0O2bAB7ed0B3abZY4t3WZstwVedAux5n4eT3cv4MKvX5rVl57GlhT9KWADgOAZpsLk82gLFvlQqR4NoFyIYdgTHGMFkPG6EG8Py6OOWQ:1swacl:K3a54OiGgIO2easIqaR3QLD5RUv8ly9McT_CJFkLG6E", "expire_date": "2024-10-18T05:13:07.147Z"}}, {"model": "sessions.session", "pk": "kwms7mwv21c9joowjiruwmj72wmfk8ta", "fields": {"session_data": ".eJxVjDsOwjAQBe_iGll28JeSPmew1rtrHECOFCcV4u4QKQW0b2beSyTY1pq2zkuaSFyE9uL0O2bAB7ed0B3abZY4t3WZstwVedAux5n4eT3cv4MKvX5rVl57GlhT9KWADgOAZpsLk82gLFvlQqR4NoFyIYdgTHGMFkPG6EG8Py6OOWQ:1swahe:dyYp9q6THa2seQQEvJn7M6DU9rcZVFIjyrkSfM2_HaY", "expire_date": "2024-10-18T05:18:10.022Z"}}, {"model": "sessions.session", "pk": "ljc8vuhcahm1caw6hytzqfmb6pnfo56o", "fields": {"session_data": ".eJxVjMsOwiAQRf-FtSFAGBhcuvcbCI8ZqRqalHZl_Hdt0oVu7znnvkRM29riNmiJUxVnoZ04_Y45lQf1ndR76rdZlrmvy5TlrsiDDnmdKz0vh_t30NJo35otIBugGqpmrmQhO8aknHJMBiAAFIvGGwRPmJMKygNzDoyarUPx_gAWHzgK:1svVmd:Nz21X88kS5a6SywS2N8E8Li4r5F_MXM452D0AI4vFmk", "expire_date": "2024-10-15T05:50:51.430Z"}}, {"model": "sessions.session", "pk": "mi2juz2bsqyvzj0c2tk8pu9exjz51xkd", "fields": {"session_data": ".eJxVjDsOwjAQBe_iGll28JeSPmew1rtrHECOFCcV4u4QKQW0b2beSyTY1pq2zkuaSFyE9uL0O2bAB7ed0B3abZY4t3WZstwVedAux5n4eT3cv4MKvX5rVl57GlhT9KWADgOAZpsLk82gLFvlQqR4NoFyIYdgTHGMFkPG6EG8Py6OOWQ:1swaXb:MwztaNWjAZiaru1YbiFyFSpVUruQ8d_py83N-OHNYzQ", "expire_date": "2024-10-18T05:07:47.665Z"}}, {"model": "sessions.session", "pk": "mltqagzym1d1k8wiwwxwvo2xrjvc00st", "fields": {"session_data": ".eJxVjDsOwjAQBe_iGll28JeSPmew1rtrHECOFCcV4u4QKQW0b2beSyTY1pq2zkuaSFyE9uL0O2bAB7ed0B3abZY4t3WZstwVedAux5n4eT3cv4MKvX5rVl57GlhT9KWADgOAZpsLk82gLFvlQqR4NoFyIYdgTHGMFkPG6EG8Py6OOWQ:1swaT9:Grj9MGX5EzkAvq7erqLmtKTAs5jU6-UZWV6aALK8x64", "expire_date": "2024-10-18T05:03:11.862Z"}}, {"model": "sessions.session", "pk": "mxv2azqz52sgnur83q65gtvax5qn8s2u", "fields": {"session_data": ".eJxVjDsOwjAQBe_iGll28JeSPmew1rtrHECOFCcV4u4QKQW0b2beSyTY1pq2zkuaSFyE9uL0O2bAB7ed0B3abZY4t3WZstwVedAux5n4eT3cv4MKvX5rVl57GlhT9KWADgOAZpsLk82gLFvlQqR4NoFyIYdgTHGMFkPG6EG8Py6OOWQ:1swab6:tyJ3ny3Jv2INy240xX1_bw_vctVyBeVj-e-jEy1GzeI", "expire_date": "2024-10-18T05:11:24.903Z"}}, {"model": "sessions.session", "pk": "nlkmy7msfuo9i2k5m052bgjwbhefagi5", "fields": {"session_data": ".eJxVjDsOwjAQBe_iGll28JeSPmew1rtrHECOFCcV4u4QKQW0b2beSyTY1pq2zkuaSFyE9uL0O2bAB7ed0B3abZY4t3WZstwVedAux5n4eT3cv4MKvX5rVl57GlhT9KWADgOAZpsLk82gLFvlQqR4NoFyIYdgTHGMFkPG6EG8Py6OOWQ:1swafI:tvdUZozoAG9IYeUxSl8O1Gn-bVSvUri5FPpzj63RWt4", "expire_date": "2024-10-18T05:15:44.829Z"}}, {"model": "sessions.session", "pk": "nq06cp1k7pjqho7w3qmwdlfsn8wx0k19", "fields": {"session_data": ".eJxVjDsOwjAQBe_iGll28JeSPmew1rtrHECOFCcV4u4QKQW0b2beSyTY1pq2zkuaSFyE9uL0O2bAB7ed0B3abZY4t3WZstwVedAux5n4eT3cv4MKvX5rVl57GlhT9KWADgOAZpsLk82gLFvlQqR4NoFyIYdgTHGMFkPG6EG8Py6OOWQ:1swaWk:uFhaedU0uAXiFbcQlRKHDc4KvNnmNgEzwfNryVR2CZY", "expire_date": "2024-10-18T05:06:54.860Z"}}, {"model": "sessions.session", "pk": "pdm7djblyblurk3vrue7w86ixaszxwpe", "fields": {"session_data": ".eJxVjDsOwjAQBe_iGll28JeSPmew1rtrHECOFCcV4u4QKQW0b2beSyTY1pq2zkuaSFyE9uL0O2bAB7ed0B3abZY4t3WZstwVedAux5n4eT3cv4MKvX5rVl57GlhT9KWADgOAZpsLk82gLFvlQqR4NoFyIYdgTHGMFkPG6EG8Py6OOWQ:1swaY7:RaGWgHldWxcOM12UZjUYZSH5H4l5gGY5p7U3GnP1Uf0", "expire_date": "2024-10-18T05:08:19.642Z"}}, {"model": "sessions.session", "pk": "qf9a4hda3nekw6bnqdw94lvoeldn995i", "fields": {"session_data": ".eJxVjDsOwjAQBe_iGll28JeSPmew1rtrHECOFCcV4u4QKQW0b2beSyTY1pq2zkuaSFyE9uL0O2bAB7ed0B3abZY4t3WZstwVedAux5n4eT3cv4MKvX5rVl57GlhT9KWADgOAZpsLk82gLFvlQqR4NoFyIYdgTHGMFkPG6EG8Py6OOWQ:1swaTA:mQBlH0ZLge4vjpfC5ihiUgk-hyNZq9uhpbNj-_f-lck", "expire_date": "2024-10-18T05:03:12.278Z"}}, {"model": "sessions.session", "pk": "qj16lpsel1lawq5ed8hd1ysie57ruzeg", "fields": {"session_data": ".eJxVjDsOwjAQBe_iGll28JeSPmew1rtrHECOFCcV4u4QKQW0b2beSyTY1pq2zkuaSFyE9uL0O2bAB7ed0B3abZY4t3WZstwVedAux5n4eT3cv4MKvX5rVl57GlhT9KWADgOAZpsLk82gLFvlQqR4NoFyIYdgTHGMFkPG6EG8Py6OOWQ:1swack:tvABwMX-FyAIQpFs4Btv1exe1-kx0Qo_bePTYKFsLbo", "expire_date": "2024-10-18T05:13:06.978Z"}}, {"model": "sessions.session", "pk": "qmdl99o438cqycych27ebus05i98qjxi", "fields": {"session_data": ".eJxVjDsOwjAQBe_iGll28JeSPmew1rtrHECOFCcV4u4QKQW0b2beSyTY1pq2zkuaSFyE9uL0O2bAB7ed0B3abZY4t3WZstwVedAux5n4eT3cv4MKvX5rVl57GlhT9KWADgOAZpsLk82gLFvlQqR4NoFyIYdgTHGMFkPG6EG8Py6OOWQ:1swaTA:mQBlH0ZLge4vjpfC5ihiUgk-hyNZq9uhpbNj-_f-lck", "expire_date": "2024-10-18T05:03:12.816Z"}}, {"model": "sessions.session", "pk": "r0ct49bqc0zi7ixstcbhm26i9taj5kl0", "fields": {"session_data": ".eJxVjDsOwjAQBe_iGll28JeSPmew1rtrHECOFCcV4u4QKQW0b2beSyTY1pq2zkuaSFyE9uL0O2bAB7ed0B3abZY4t3WZstwVedAux5n4eT3cv4MKvX5rVl57GlhT9KWADgOAZpsLk82gLFvlQqR4NoFyIYdgTHGMFkPG6EG8Py6OOWQ:1swaXb:MwztaNWjAZiaru1YbiFyFSpVUruQ8d_py83N-OHNYzQ", "expire_date": "2024-10-18T05:07:47.882Z"}}, {"model": "sessions.session", "pk": "ruhtfenfkkvwaazhyzn4rsxx68y5ehkk", "fields": {"session_data": ".eJxVjDsOwjAQBe_iGll28JeSPmew1rtrHECOFCcV4u4QKQW0b2beSyTY1pq2zkuaSFyE9uL0O2bAB7ed0B3abZY4t3WZstwVedAux5n4eT3cv4MKvX5rVl57GlhT9KWADgOAZpsLk82gLFvlQqR4NoFyIYdgTHGMFkPG6EG8Py6OOWQ:1swafI:tvdUZozoAG9IYeUxSl8O1Gn-bVSvUri5FPpzj63RWt4", "expire_date": "2024-10-18T05:15:44.767Z"}}, {"model": "sessions.session", "pk": "scejglfaw1k7o025s65ftp569zxor7ar", "fields": {"session_data": ".eJxVjDsOwjAQBe_iGll28JeSPmew1rtrHECOFCcV4u4QKQW0b2beSyTY1pq2zkuaSFyE9uL0O2bAB7ed0B3abZY4t3WZstwVedAux5n4eT3cv4MKvX5rVl57GlhT9KWADgOAZpsLk82gLFvlQqR4NoFyIYdgTHGMFkPG6EG8Py6OOWQ:1swaXb:MwztaNWjAZiaru1YbiFyFSpVUruQ8d_py83N-OHNYzQ", "expire_date": "2024-10-18T05:07:47.967Z"}}, {"model": "sessions.session", "pk": "sjbqfjqnczfaq6qr2nmgxamxnjng67aa", "fields": {"session_data": ".eJxVjDsOwjAQBe_iGll28JeSPmew1rtrHECOFCcV4u4QKQW0b2beSyTY1pq2zkuaSFyE9uL0O2bAB7ed0B3abZY4t3WZstwVedAux5n4eT3cv4MKvX5rVl57GlhT9KWADgOAZpsLk82gLFvlQqR4NoFyIYdgTHGMFkPG6EG8Py6OOWQ:1swack:tvABwMX-FyAIQpFs4Btv1exe1-kx0Qo_bePTYKFsLbo", "expire_date": "2024-10-18T05:13:06.868Z"}}, {"model": "sessions.session", "pk": "soe80h87j95z4t5lutmaqpvufvkzwy2g", "fields": {"session_data": ".eJxVjMEKwyAQRP_Fc5G4RjE99t5vENdda9qiEJNT6L_XQA4tcxiYNzO78GFbs98aL34mcRXKiMtviCG-uByEnqE8qoy1rMuM8qjIkzZ5r8Tv29n9O8ih5b4Omt04JKtMhGDsCMgEzoLCQTkAh-CSdgrIqk504kiTiV3YnScUny_4ZTgy:1svVuM:6Yc28DiFXhz1t9vERh4S0CdDsjWc6WRUlL3JyxPlqh0", "expire_date": "2024-10-15T05:58:50.524Z"}}, {"model": "sessions.session", "pk": "t5b0lqo7c8ewe904i8seldngfvudhgi1", "fields": {"session_data": ".eJxVjEEOwiAQRe_C2hAodKAu3XsGMsOAVA0kpV0Z765NutDtf-_9lwi4rSVsPS1hZnEWIE6_G2F8pLoDvmO9NRlbXZeZ5K7Ig3Z5bZyel8P9OyjYy7fW6A0pzj5rH60xNGQ7ko4TMVpQgMgMQ7LeWQXgtIcMo3cGclYTaRTvD-ktN6o:1sujOr:sFtlWTn3q_UF6pl0ohqotqqywXU1f72s7j9OEZyzhhM", "expire_date": "2024-10-13T02:11:05.877Z"}}, {"model": "sessions.session", "pk": "t7fsndc8v0rushanrozribyyso5zdgnx", "fields": {"session_data": ".eJxVjDsOwjAQBe_iGll28JeSPmew1rtrHECOFCcV4u4QKQW0b2beSyTY1pq2zkuaSFyE9uL0O2bAB7ed0B3abZY4t3WZstwVedAux5n4eT3cv4MKvX5rVl57GlhT9KWADgOAZpsLk82gLFvlQqR4NoFyIYdgTHGMFkPG6EG8Py6OOWQ:1swaTr:X7rY0hOFl7_gTZm3ozyvgNk0Xs7bNZyRVJgfKHmA7gI", "expire_date": "2024-10-18T05:03:55.485Z"}}, {"model": "sessions.session", "pk": "tpp9tah0golmm9a9jix86th62d54xe7p", "fields": {"session_data": ".eJxVjDsOwjAQBe_iGll28JeSPmew1rtrHECOFCcV4u4QKQW0b2beSyTY1pq2zkuaSFyE9uL0O2bAB7ed0B3abZY4t3WZstwVedAux5n4eT3cv4MKvX5rVl57GlhT9KWADgOAZpsLk82gLFvlQqR4NoFyIYdgTHGMFkPG6EG8Py6OOWQ:1swafI:tvdUZozoAG9IYeUxSl8O1Gn-bVSvUri5FPpzj63RWt4", "expire_date": "2024-10-18T05:15:44.986Z"}}, {"model": "sessions.session", "pk": "tx2cv10pm8vastijmn8x7x73jw783e5r", "fields": {"session_data": ".eJxVjDsOwjAQBe_iGll28JeSPmew1rtrHECOFCcV4u4QKQW0b2beSyTY1pq2zkuaSFyE9uL0O2bAB7ed0B3abZY4t3WZstwVedAux5n4eT3cv4MKvX5rVl57GlhT9KWADgOAZpsLk82gLFvlQqR4NoFyIYdgTHGMFkPG6EG8Py6OOWQ:1swaT9:Grj9MGX5EzkAvq7erqLmtKTAs5jU6-UZWV6aALK8x64", "expire_date": "2024-10-18T05:03:11.861Z"}}, {"model": "sessions.session", "pk": "u42o7qtsj0lwruzhaaye8woitb8oc2ib", "fields": {"session_data": ".eJxVjDsOwjAQBe_iGll28JeSPmew1rtrHECOFCcV4u4QKQW0b2beSyTY1pq2zkuaSFyE9uL0O2bAB7ed0B3abZY4t3WZstwVedAux5n4eT3cv4MKvX5rVl57GlhT9KWADgOAZpsLk82gLFvlQqR4NoFyIYdgTHGMFkPG6EG8Py6OOWQ:1swaWk:uFhaedU0uAXiFbcQlRKHDc4KvNnmNgEzwfNryVR2CZY", "expire_date": "2024-10-18T05:06:54.764Z"}}, {"model": "sessions.session", "pk": "udhv7xe1w1t143zgje2yvq2a18t4crjf", "fields": {"session_data": ".eJxVjDsOwjAQBe_iGll28JeSPmew1rtrHECOFCcV4u4QKQW0b2beSyTY1pq2zkuaSFyE9uL0O2bAB7ed0B3abZY4t3WZstwVedAux5n4eT3cv4MKvX5rVl57GlhT9KWADgOAZpsLk82gLFvlQqR4NoFyIYdgTHGMFkPG6EG8Py6OOWQ:1sw9me:VmbQKKsKV-ZwkH1hg63TyChCQLuUL7ksZHZbzCX8hJ8", "expire_date": "2024-10-17T00:33:32.752Z"}}, {"model": "sessions.session", "pk": "utadldtsuv6cxqe9q5p27jy3huq4gktz", "fields": {"session_data": ".eJxVjDsOwjAQBe_iGll28JeSPmew1rtrHECOFCcV4u4QKQW0b2beSyTY1pq2zkuaSFyE9uL0O2bAB7ed0B3abZY4t3WZstwVedAux5n4eT3cv4MKvX5rVl57GlhT9KWADgOAZpsLk82gLFvlQqR4NoFyIYdgTHGMFkPG6EG8Py6OOWQ:1swaTE:sBN5s_6yR7lnhwJvZGQA8eseaPiXdml6Yw1pyVqI11I", "expire_date": "2024-10-18T05:03:16.008Z"}}, {"model": "sessions.session", "pk": "v1uc3ek9mdticqpl6z55wv2qg0gitr4b", "fields": {"session_data": ".eJxVjDsOwjAQBe_iGll28JeSPmew1rtrHECOFCcV4u4QKQW0b2beSyTY1pq2zkuaSFyE9uL0O2bAB7ed0B3abZY4t3WZstwVedAux5n4eT3cv4MKvX5rVl57GlhT9KWADgOAZpsLk82gLFvlQqR4NoFyIYdgTHGMFkPG6EG8Py6OOWQ:1swaTC:LZVudj7tKuHA6sPgvO_OGO9iP60RlvpReRvYcZWj3jE", "expire_date": "2024-10-18T05:03:14.306Z"}}, {"model": "sessions.session", "pk": "vb5eifphcrb0scdcjyrelkhs22mi76x9", "fields": {"session_data": ".eJxVjDsOwjAQBe_iGll28JeSPmew1rtrHECOFCcV4u4QKQW0b2beSyTY1pq2zkuaSFyE9uL0O2bAB7ed0B3abZY4t3WZstwVedAux5n4eT3cv4MKvX5rVl57GlhT9KWADgOAZpsLk82gLFvlQqR4NoFyIYdgTHGMFkPG6EG8Py6OOWQ:1swaVN:Suzb0zksi4J4otTjTebDqKvxVMr1jrZjOf_7kVgMeGw", "expire_date": "2024-10-18T05:05:29.751Z"}}, {"model": "sessions.session", "pk": "velh8wbwse7yqqmzxebff2io0rxn9knw", "fields": {"session_data": ".eJxVjDsOwjAQBe_iGll28JeSPmew1rtrHECOFCcV4u4QKQW0b2beSyTY1pq2zkuaSFyE9uL0O2bAB7ed0B3abZY4t3WZstwVedAux5n4eT3cv4MKvX5rVl57GlhT9KWADgOAZpsLk82gLFvlQqR4NoFyIYdgTHGMFkPG6EG8Py6OOWQ:1swaTF:NZhK7tJ6-2HvnqYBgfeSXWaYyMR-SWO1gsDLoso0s00", "expire_date": "2024-10-18T05:03:17.028Z"}}, {"model": "sessions.session", "pk": "vqbfa9rz9kaykp1izv9mh8sotlb89be7", "fields": {"session_data": ".eJxVjMEOwiAQRP-FsyFduxTq0bvfQNhdkKqhSWlPxn-XJj3ocea9mbfyYVuz32pc_CTqokCdfjsK_IxlB_II5T5rnsu6TKR3RR-06tss8XU93L-DHGpuawMUATtCICsGsKchOIc8tEChY4sRG8OEyY3ozmMvyCwW2LDBBOrzBdLdN5U:1sthm0:Cl7qiwuFvPZIdToiGkwaAHohbv9FT0RbauljhwdLUGA", "expire_date": "2024-10-10T06:14:44.902Z"}}, {"model": "sessions.session", "pk": "vznd9rhce4ghlc78q3fderr8sce5jdio", "fields": {"session_data": ".eJxVjDsOwjAQBe_iGll28JeSPmew1rtrHECOFCcV4u4QKQW0b2beSyTY1pq2zkuaSFyE9uL0O2bAB7ed0B3abZY4t3WZstwVedAux5n4eT3cv4MKvX5rVl57GlhT9KWADgOAZpsLk82gLFvlQqR4NoFyIYdgTHGMFkPG6EG8Py6OOWQ:1swaVN:Suzb0zksi4J4otTjTebDqKvxVMr1jrZjOf_7kVgMeGw", "expire_date": "2024-10-18T05:05:29.367Z"}}, {"model": "sessions.session", "pk": "w2bnfk4v0gqyi4m2zo2rygjfbhh9bxmf", "fields": {"session_data": ".eJxVjMEOwiAQRP-FsyFduxTq0bvfQNhdkKqhSWlPxn-XJj3ocea9mbfyYVuz32pc_CTqokCdfjsK_IxlB_II5T5rnsu6TKR3RR-06tss8XU93L-DHGpuawMUATtCICsGsKchOIc8tEChY4sRG8OEyY3ozmMvyCwW2LDBBOrzBdLdN5U:1sv7JL:5vm9Y1kgWUstQYtoQPEMYRr4cAkA0xaovk4j54O-fn0", "expire_date": "2024-10-14T03:42:59.184Z"}}, {"model": "sessions.session", "pk": "wnshy3icxd43qadp4d7j64mvfsdyma11", "fields": {"session_data": ".eJxVjDsOwjAQBe_iGll28JeSPmew1rtrHECOFCcV4u4QKQW0b2beSyTY1pq2zkuaSFyE9uL0O2bAB7ed0B3abZY4t3WZstwVedAux5n4eT3cv4MKvX5rVl57GlhT9KWADgOAZpsLk82gLFvlQqR4NoFyIYdgTHGMFkPG6EG8Py6OOWQ:1swaYX:GZfnOp_wFhupRNkmcRcLngymidxqfxukdN2GBSFOWLA", "expire_date": "2024-10-18T05:08:45.862Z"}}, {"model": "sessions.session", "pk": "xa4kgk2d1jq3gh12afposd8ligoyudst", "fields": {"session_data": ".eJxVjMEOwiAQRP-FsyFduxTq0bvfQNhdkKqhSWlPxn-XJj3ocea9mbfyYVuz32pc_CTqokCdfjsK_IxlB_II5T5rnsu6TKR3RR-06tss8XU93L-DHGpuawMUATtCICsGsKchOIc8tEChY4sRG8OEyY3ozmMvyCwW2LDBBOrzBdLdN5U:1stz3C:FUqiSzsrW2jlBqirx1qRwglcsRCiwPyLG0GRm7wgHsc", "expire_date": "2024-10-11T00:41:38.941Z"}}, {"model": "sessions.session", "pk": "xn4n3hs0z6t3ebga4bx12sm6z97tjxp5", "fields": {"session_data": ".eJxVjDsOwjAQBe_iGll28JeSPmew1rtrHECOFCcV4u4QKQW0b2beSyTY1pq2zkuaSFyE9uL0O2bAB7ed0B3abZY4t3WZstwVedAux5n4eT3cv4MKvX5rVl57GlhT9KWADgOAZpsLk82gLFvlQqR4NoFyIYdgTHGMFkPG6EG8Py6OOWQ:1swaTA:mQBlH0ZLge4vjpfC5ihiUgk-hyNZq9uhpbNj-_f-lck", "expire_date": "2024-10-18T05:03:12.668Z"}}, {"model": "sessions.session", "pk": "xsz0tubhn6nllnq3xsyn86u10dcewjdt", "fields": {"session_data": "e30:1swaT5:NYk226olOIXdi3AULfctRtl-vWwP3Hwsdt8XiKBVNSM", "expire_date": "2024-10-18T05:03:07.579Z"}}, {"model": "sessions.session", "pk": "ytpe51dsyc24xmrm8qkbdjni5s11c5ea", "fields": {"session_data": ".eJxVjDsOwjAQBe_iGll28JeSPmew1rtrHECOFCcV4u4QKQW0b2beSyTY1pq2zkuaSFyE9uL0O2bAB7ed0B3abZY4t3WZstwVedAux5n4eT3cv4MKvX5rVl57GlhT9KWADgOAZpsLk82gLFvlQqR4NoFyIYdgTHGMFkPG6EG8Py6OOWQ:1swab7:b4Ejx6iJumW0XaueEE2Igpr1T__BsuuYwLyQ0upgfPM", "expire_date": "2024-10-18T05:11:25.639Z"}}, {"model": "sessions.session", "pk": "yvazfyjkan76w5juowgyu1ftrxsow16t", "fields": {"session_data": ".eJxVjDsOwjAQBe_iGll28JeSPmew1rtrHECOFCcV4u4QKQW0b2beSyTY1pq2zkuaSFyE9uL0O2bAB7ed0B3abZY4t3WZstwVedAux5n4eT3cv4MKvX5rVl57GlhT9KWADgOAZpsLk82gLFvlQqR4NoFyIYdgTHGMFkPG6EG8Py6OOWQ:1swaVN:Suzb0zksi4J4otTjTebDqKvxVMr1jrZjOf_7kVgMeGw", "expire_date": "2024-10-18T05:05:29.604Z"}}, {"model": "sessions.session", "pk": "zpt14fs290ov725bfxmn7bkqw1jbu6q5", "fields": {"session_data": ".eJxVjDsOwjAQBe_iGll28JeSPmew1rtrHECOFCcV4u4QKQW0b2beSyTY1pq2zkuaSFyE9uL0O2bAB7ed0B3abZY4t3WZstwVedAux5n4eT3cv4MKvX5rVl57GlhT9KWADgOAZpsLk82gLFvlQqR4NoFyIYdgTHGMFkPG6EG8Py6OOWQ:1swahF:M0JkNPtllfT1VgfXltaqhV_0bg1mLtF2aXeXb31vPGk", "expire_date": "2024-10-18T05:17:45.708Z"}}, {"model": "milble_app.unit", "pk": 15, "fields": {"name": "test", "answer1": "test", "answer2": "test", "answer3": "test", "subscriber_count": 1}}, {"model": "milble_app.category", "pk": 1, "fields": {"name": "자유"}}, {"model": "milble_app.customuser", "pk": 13, "fields": {"password": "pbkdf2_sha256$260000$Df6D734Dj7xybCt9Vh2S4S$xUdqEvt1/nIsS6HRdPnI54x1cT797c7atpiIKdtqUgA=", "last_login": "2024-10-04T04:18:23.322Z", "is_superuser": true, "username": "wlstndydz", "first_name": "", "last_name": "", "email": "wlstndyd616@gmail.com", "is_staff": true, "is_active": true, "date_joined": "2024-10-01T01:40:02.425Z", "unit": null, "groups": [], "user_permissions": []}}, {"model": "milble_app.customuser", "pk": 17, "fields": {"password": "pbkdf2_sha256$260000$hIY4e4xl5UJSlPmkdaoaMA$dL21RS6xqDq+2zViYhxF9Yf5Al9DJ+FMaxIBVbeGMno=", "last_login": "2024-10-04T05:18:10.227Z", "is_superuser": false, "username": "test", "first_name": "", "last_name": "", "email": "", "is_staff": false, "is_active": true, "date_joined": "2024-10-03T00:33:25.217Z", "unit": 15, "groups": [], "user_permissions": []}}, {"model": "milble_app.post", "pk": 24, "fields": {"title": "test", "content": "test", "created_at": "2024-10-03T00:33:53.417Z", "updated_at": "2024-10-04T05:19:08.425Z", "author": "test", "unit": 15, "category": null, "likes": 0, "comments_count": 49, "views": 1109, "liked_users": []}}, {"model": "milble_app.post", "pk": 25, "fields": {"title": "1234", "content": "1234", "created_at": "2024-10-03T00:33:58.725Z", "updated_at": "2024-10-04T05:19:07.702Z", "author": "test", "unit": 15, "category": 1, "likes": 1, "comments_count": 0, "views": 486, "liked_users": [17]}}, {"model": "milble_app.post", "pk": 26, "fields": {"title": "test2123", "content": "test1234", "created_at": "2024-10-03T00:34:07.508Z", "updated_at": "2024-10-04T05:19:08.099Z", "author": "test", "unit": 15, "category": 1, "likes": 0, "comments_count": 0, "views": 497, "liked_users": []}}, {"model": "milble_app.post", "pk": 27, "fields": {"title": "1234", "content": "1234", "created_at": "2024-10-03T00:36:18.960Z", "updated_at": "2024-10-04T05:19:08.233Z", "author": "test", "unit": 15, "category": null, "likes": 1, "comments_count": 0, "views": 466, "liked_users": []}}, {"model": "milble_app.comment", "pk": 8, "fields": {"post": 24, "content": "test", "created_at": "2024-10-04T04:45:26.579Z", "author": "test", "unit": "test"}}, {"model": "milble_app.comment", "pk": 9, "fields": {"post": 24, "content": "This is a test comment.", "created_at": "2024-10-04T05:05:33.553Z", "author": "test", "unit": "test"}}, {"model": "milble_app.comment", "pk": 10, "fields": {"post": 24, "content": "This is a test comment.", "created_at": "2024-10-04T05:05:33.822Z", "author": "test", "unit": "test"}}, {"model": "milble_app.comment", "pk": 11, "fields": {"post": 24, "content": "This is a test comment.", "created_at": "2024-10-04T05:05:34.304Z", "author": "test", "unit": "test"}}, {"model": "milble_app.comment", "pk": 12, "fields": {"post": 24, "content": "This is a test comment.", "created_at": "2024-10-04T05:05:35.216Z", "author": "test", "unit": "test"}}, {"model": "milble_app.comment", "pk": 13, "fields": {"post": 24, "content": "This is a test comment.", "created_at": "2024-10-04T05:05:35.996Z", "author": "test", "unit": "test"}}, {"model": "milble_app.comment", "pk": 14, "fields": {"post": 24, "content": "This is a test comment.", "created_at": "2024-10-04T05:05:39.957Z", "author": "test", "unit": "test"}}, {"model": "milble_app.comment", "pk": 15, "fields": {"post": 24, "content": "This is a test comment.", "created_at": "2024-10-04T05:05:40.195Z", "author": "test", "unit": "test"}}, {"model": "milble_app.comment", "pk": 16, "fields": {"post": 24, "content": "This is a test comment.", "created_at": "2024-10-04T05:05:40.948Z", "author": "test", "unit": "test"}}, {"model": "milble_app.comment", "pk": 17, "fields": {"post": 24, "content": "This is a test comment.", "created_at": "2024-10-04T05:18:13.340Z", "author": "test", "unit": "test"}}, {"model": "milble_app.comment", "pk": 18, "fields": {"post": 24, "content": "This is a test comment.", "created_at": "2024-10-04T05:18:14.685Z", "author": "test", "unit": "test"}}, {"model": "milble_app.comment", "pk": 19, "fields": {"post": 24, "content": "This is a test comment.", "created_at": "2024-10-04T05:18:14.764Z", "author": "test", "unit": "test"}}, {"model": "milble_app.comment", "pk": 20, "fields": {"post": 24, "content": "This is a test comment.", "created_at": "2024-10-04T05:18:15.120Z", "author": "test", "unit": "test"}}, {"model": "milble_app.comment", "pk": 21, "fields": {"post": 24, "content": "This is a test comment.", "created_at": "2024-10-04T05:18:16.292Z", "author": "test", "unit": "test"}}, {"model": "milble_app.comment", "pk": 22, "fields": {"post": 24, "content": "This is a test comment.", "created_at": "2024-10-04T05:18:19.790Z", "author": "test", "unit": "test"}}, {"model": "milble_app.comment", "pk": 23, "fields": {"post": 24, "content": "This is a test comment.", "created_at": "2024-10-04T05:18:20.989Z", "author": "test", "unit": "test"}}, {"model": "milble_app.comment", "pk": 24, "fields": {"post": 24, "content": "This is a test comment.", "created_at": "2024-10-04T05:18:21.051Z", "author": "test", "unit": "test"}}, {"model": "milble_app.comment", "pk": 25, "fields": {"post": 24, "content": "This is a test comment.", "created_at": "2024-10-04T05:18:22.087Z", "author": "test", "unit": "test"}}, {"model": "milble_app.comment", "pk": 26, "fields": {"post": 24, "content": "This is a test comment.", "created_at": "2024-10-04T05:18:24.352Z", "author": "test", "unit": "test"}}, {"model": "milble_app.comment", "pk": 27, "fields": {"post": 24, "content": "This is a test comment.", "created_at": "2024-10-04T05:18:27.219Z", "author": "test", "unit": "test"}}, {"model": "milble_app.comment", "pk": 28, "fields": {"post": 24, "content": "This is a test comment.", "created_at": "2024-10-04T05:18:28.196Z", "author": "test", "unit": "test"}}, {"model": "milble_app.comment", "pk": 29, "fields": {"post": 24, "content": "This is a test comment.", "created_at": "2024-10-04T05:18:28.636Z", "author": "test", "unit": "test"}}, {"model": "milble_app.comment", "pk": 30, "fields": {"post": 24, "content": "This is a test comment.", "created_at": "2024-10-04T05:18:29.144Z", "author": "test", "unit": "test"}}, {"model": "milble_app.comment", "pk": 31, "fields": {"post": 24, "content": "This is a test comment.", "created_at": "2024-10-04T05:18:30.837Z", "author": "test", "unit": "test"}}, {"model": "milble_app.comment", "pk": 32, "fields": {"post": 24, "content": "This is a test comment.", "created_at": "2024-10-04T05:18:34.250Z", "author": "test", "unit": "test"}}, {"model": "milble_app.comment", "pk": 33, "fields": {"post": 24, "content": "This is a test comment.", "created_at": "2024-10-04T05:18:35.251Z", "author": "test", "unit": "test"}}, {"model": "milble_app.comment", "pk": 34, "fields": {"post": 24, "content": "This is a test comment.", "created_at": "2024-10-04T05:18:36.170Z", "author": "test", "unit": "test"}}, {"model": "milble_app.comment", "pk": 35, "fields": {"post": 24, "content": "This is a test comment.", "created_at": "2024-10-04T05:18:36.470Z", "author": "test", "unit": "test"}}, {"model": "milble_app.comment", "pk": 36, "fields": {"post": 24, "content": "This is a test comment.", "created_at": "2024-10-04T05:18:36.894Z", "author": "test", "unit": "test"}}, {"model": "milble_app.comment", "pk": 37, "fields": {"post": 24, "content": "This is a test comment.", "created_at": "2024-10-04T05:18:41.375Z", "author": "test", "unit": "test"}}, {"model": "milble_app.comment", "pk": 38, "fields": {"post": 24, "content": "This is a test comment.", "created_at": "2024-10-04T05:18:41.726Z", "author": "test", "unit": "test"}}, {"model": "milble_app.comment", "pk": 39, "fields": {"post": 24, "content": "This is a test comment.", "created_at": "2024-10-04T05:18:42.140Z", "author": "test", "unit": "test"}}, {"model": "milble_app.comment", "pk": 40, "fields": {"post": 24, "content": "This is a test comment.", "created_at": "2024-10-04T05:18:43.193Z", "author": "test", "unit": "test"}}, {"model": "milble_app.comment", "pk": 41, "fields": {"post": 24, "content": "This is a test comment.", "created_at": "2024-10-04T05:18:43.675Z", "author": "test", "unit": "test"}}, {"model": "milble_app.comment", "pk": 42, "fields": {"post": 24, "content": "This is a test comment.", "created_at": "2024-10-04T05:18:47.744Z", "author": "test", "unit": "test"}}, {"model": "milble_app.comment", "pk": 43, "fields": {"post": 24, "content": "This is a test comment.", "created_at": "2024-10-04T05:18:48.818Z", "author": "test", "unit": "test"}}, {"model": "milble_app.comment", "pk": 44, "fields": {"post": 24, "content": "This is a test comment.", "created_at": "2024-10-04T05:18:50.522Z", "author": "test", "unit": "test"}}, {"model": "milble_app.comment", "pk": 45, "fields": {"post": 24, "content": "This is a test comment.", "created_at": "2024-10-04T05:18:50.699Z", "author": "test", "unit": "test"}}, {"model": "milble_app.comment", "pk": 46, "fields": {"post": 24, "content": "This is a test comment.", "created_at": "2024-10-04T05:18:51.306Z", "author": "test", "unit": "test"}}, {"model": "milble_app.comment", "pk": 47, "fields": {"post": 24, "content": "This is a test comment.", "created_at": "2024-10-04T05:18:54.697Z", "author": "test", "unit": "test"}}, {"model": "milble_app.comment", "pk": 48, "fields": {"post": 24, "content": "This is a test comment.", "created_at": "2024-10-04T05:18:56.774Z", "author": "test", "unit": "test"}}, {"model": "milble_app.comment", "pk": 49, "fields": {"post": 24, "content": "This is a test comment.", "created_at": "2024-10-04T05:18:57.090Z", "author": "test", "unit": "test"}}, {"model": "milble_app.comment", "pk": 50, "fields": {"post": 24, "content": "This is a test comment.", "created_at": "2024-10-04T05:18:57.308Z", "author": "test", "unit": "test"}}, {"model": "milble_app.comment", "pk": 51, "fields": {"post": 24, "content": "This is a test comment.", "created_at": "2024-10-04T05:18:58.374Z", "author": "test", "unit": "test"}}, {"model": "milble_app.comment", "pk": 52, "fields": {"post": 24, "content": "This is a test comment.", "created_at": "2024-10-04T05:19:01.675Z", "author": "test", "unit": "test"}}, {"model": "milble_app.comment", "pk": 53, "fields": {"post": 24, "content": "This is a test comment.", "created_at": "2024-10-04T05:19:02.443Z", "author": "test", "unit": "test"}}, {"model": "milble_app.comment", "pk": 54, "fields": {"post": 24, "content": "This is a test comment.", "created_at": "2024-10-04T05:19:04.096Z", "author": "test", "unit": "test"}}, {"model": "milble_app.comment", "pk": 55, "fields": {"post": 24, "content": "This is a test comment.", "created_at": "2024-10-04T05:19:04.558Z", "author": "test", "unit": "test"}}, {"model": "milble_app.comment", "pk": 56, "fields": {"post": 24, "content": "This is a test comment.", "created_at": "2024-10-04T05:19:06.965Z", "author": "test", "unit": "test"}}]